nextbike_api/__init__.py
nextbike_api/client.py
nextbike_api/exceptions.py
nextbike_api/utils/__init__.py
nextbike_api/utils/state.py
nextbike_api-1.0.0.dist-info/LICENSE
nextbike_api-1.0.0.dist-info/METADATA
nextbike_api-1.0.0.dist-info/WHEEL
nextbike_api-1.0.0.dist-info/top_level.txt
nextbike_api-1.0.0.dist-info/RECORD
