Metadata-Version: 2.1
Name: nextbike-api
Version: 1.0.0
Summary: Nextbike API wrapper
Home-page: https://github.com/bdmbdsm/nextbike_api
Author: Bohdan Dmytriv
Author-email: bodik75@ukr.net
License: UNKNOWN
Platform: UNKNOWN
Classifier: Programming Language :: Python :: 3
Classifier: License :: OSI Approved :: MIT License
Classifier: Operating System :: OS Independent
Requires-Dist: requests (==2.22.0)
